[
  {
    "name": "Afghanistan",
    "iso3166Alpha2CountryCode": "AF",
    "iso3166Alpha3CountryCode": "AFG",
    "code": 4
  },
  {
    "name": "Albania",
    "iso3166Alpha2CountryCode": "AL",
    "iso3166Alpha3CountryCode": "ALB",
    "code": 8
  },
  {
    "name": "Algeria",
    "iso3166Alpha2CountryCode": "DZ",
    "iso3166Alpha3CountryCode": "DZA",
    "code": 12
  },
  {
    "name": "American Samoa",
    "iso3166Alpha2CountryCode": "AS",
    "iso3166Alpha3CountryCode": "ASM",
    "code": 16
  },
  {
    "name": "Andorra",
    "iso3166Alpha2CountryCode": "AD",
    "iso3166Alpha3CountryCode": "AND",
    "code": 20
  },
  {
    "name": "Angola",
    "iso3166Alpha2CountryCode": "AO",
    "iso3166Alpha3CountryCode": "AGO",
    "code": 24
  },
  {
    "name": "Anguilla",
    "iso3166Alpha2CountryCode": "AI",
    "iso3166Alpha3CountryCode": "AIA",
    "code": 660
  },
  {
    "name": "Antarctica",
    "iso3166Alpha2CountryCode": "AQ",
    "iso3166Alpha3CountryCode": "ATA",
    "code": 10
  },
  {
    "name": "Antigua and Barbuda",
    "iso3166Alpha2CountryCode": "AG",
    "iso3166Alpha3CountryCode": "ATG",
    "code": 28
  },
  {
    "name": "Argentina",
    "iso3166Alpha2CountryCode": "AR",
    "iso3166Alpha3CountryCode": "ARG",
    "code": 32
  },
  {
    "name": "Armenia",
    "iso3166Alpha2CountryCode": "AM",
    "iso3166Alpha3CountryCode": "ARM",
    "code": 51
  },
  {
    "name": "Aruba",
    "iso3166Alpha2CountryCode": "AW",
    "iso3166Alpha3CountryCode": "ABW",
    "code": 533
  },
  {
    "name": "Australia",
    "iso3166Alpha2CountryCode": "AU",
    "iso3166Alpha3CountryCode": "AUS",
    "code": 36
  },
  {
    "name": "Austria",
    "iso3166Alpha2CountryCode": "AT",
    "iso3166Alpha3CountryCode": "AUT",
    "code": 40
  },
  {
    "name": "Azerbaijan",
    "iso3166Alpha2CountryCode": "AZ",
    "iso3166Alpha3CountryCode": "AZE",
    "code": 31
  },
  {
    "name": "Bahamas (the)",
    "iso3166Alpha2CountryCode": "BS",
    "iso3166Alpha3CountryCode": "BHS",
    "code": 44
  },
  {
    "name": "Bahrain",
    "iso3166Alpha2CountryCode": "BH",
    "iso3166Alpha3CountryCode": "BHR",
    "code": 48
  },
  {
    "name": "Bangladesh",
    "iso3166Alpha2CountryCode": "BD",
    "iso3166Alpha3CountryCode": "BGD",
    "code": 50
  },
  {
    "name": "Barbados",
    "iso3166Alpha2CountryCode": "BB",
    "iso3166Alpha3CountryCode": "BRB",
    "code": 52
  },
  {
    "name": "Belarus",
    "iso3166Alpha2CountryCode": "BY",
    "iso3166Alpha3CountryCode": "BLR",
    "code": 112
  },
  {
    "name": "Belgium",
    "iso3166Alpha2CountryCode": "BE",
    "iso3166Alpha3CountryCode": "BEL",
    "code": 56
  },
  {
    "name": "Belize",
    "iso3166Alpha2CountryCode": "BZ",
    "iso3166Alpha3CountryCode": "BLZ",
    "code": 84
  },
  {
    "name": "Benin",
    "iso3166Alpha2CountryCode": "BJ",
    "iso3166Alpha3CountryCode": "BEN",
    "code": 204
  },
  {
    "name": "Bermuda",
    "iso3166Alpha2CountryCode": "BM",
    "iso3166Alpha3CountryCode": "BMU",
    "code": 60
  },
  {
    "name": "Bhutan",
    "iso3166Alpha2CountryCode": "BT",
    "iso3166Alpha3CountryCode": "BTN",
    "code": 64
  },
  {
    "name": "Bolivia (Plurinational State of)",
    "iso3166Alpha2CountryCode": "BO",
    "iso3166Alpha3CountryCode": "BOL",
    "code": 68
  },
  {
    "name": "Bonaire, Sint Eustatius and Saba",
    "iso3166Alpha2CountryCode": "BQ",
    "iso3166Alpha3CountryCode": "BES",
    "code": 535
  },
  {
    "name": "Bosnia and Herzegovina",
    "iso3166Alpha2CountryCode": "BA",
    "iso3166Alpha3CountryCode": "BIH",
    "code": 70
  },
  {
    "name": "Botswana",
    "iso3166Alpha2CountryCode": "BW",
    "iso3166Alpha3CountryCode": "BWA",
    "code": 72
  },
  {
    "name": "Bouvet Island",
    "iso3166Alpha2CountryCode": "BV",
    "iso3166Alpha3CountryCode": "BVT",
    "code": 74
  },
  {
    "name": "Brazil",
    "iso3166Alpha2CountryCode": "BR",
    "iso3166Alpha3CountryCode": "BRA",
    "code": 76
  },
  {
    "name": "British Indian Ocean Territory (the)",
    "iso3166Alpha2CountryCode": "IO",
    "iso3166Alpha3CountryCode": "IOT",
    "code": 86
  },
  {
    "name": "Brunei Darussalam",
    "iso3166Alpha2CountryCode": "BN",
    "iso3166Alpha3CountryCode": "BRN",
    "code": 96
  },
  {
    "name": "Bulgaria",
    "iso3166Alpha2CountryCode": "BG",
    "iso3166Alpha3CountryCode": "BGR",
    "code": 100
  },
  {
    "name": "Burkina Faso",
    "iso3166Alpha2CountryCode": "BF",
    "iso3166Alpha3CountryCode": "BFA",
    "code": 854
  },
  {
    "name": "Burundi",
    "iso3166Alpha2CountryCode": "BI",
    "iso3166Alpha3CountryCode": "BDI",
    "code": 108
  },
  {
    "name": "Cabo Verde",
    "iso3166Alpha2CountryCode": "CV",
    "iso3166Alpha3CountryCode": "CPV",
    "code": 132
  },
  {
    "name": "Cambodia",
    "iso3166Alpha2CountryCode": "KH",
    "iso3166Alpha3CountryCode": "KHM",
    "code": 116
  },
  {
    "name": "Cameroon",
    "iso3166Alpha2CountryCode": "CM",
    "iso3166Alpha3CountryCode": "CMR",
    "code": 120
  },
  {
    "name": "Canada",
    "iso3166Alpha2CountryCode": "CA",
    "iso3166Alpha3CountryCode": "CAN",
    "code": 124
  },
  {
    "name": "Cayman Islands (the)",
    "iso3166Alpha2CountryCode": "KY",
    "iso3166Alpha3CountryCode": "CYM",
    "code": 136
  },
  {
    "name": "Central African Republic (the)",
    "iso3166Alpha2CountryCode": "CF",
    "iso3166Alpha3CountryCode": "CAF",
    "code": 140
  },
  {
    "name": "Chad",
    "iso3166Alpha2CountryCode": "TD",
    "iso3166Alpha3CountryCode": "TCD",
    "code": 148
  },
  {
    "name": "Chile",
    "iso3166Alpha2CountryCode": "CL",
    "iso3166Alpha3CountryCode": "CHL",
    "code": 152
  },
  {
    "name": "China",
    "iso3166Alpha2CountryCode": "CN",
    "iso3166Alpha3CountryCode": "CHN",
    "code": 156
  },
  {
    "name": "Christmas Island",
    "iso3166Alpha2CountryCode": "CX",
    "iso3166Alpha3CountryCode": "CXR",
    "code": 162
  },
  {
    "name": "Cocos (Keeling) Islands (the)",
    "iso3166Alpha2CountryCode": "CC",
    "iso3166Alpha3CountryCode": "CCK",
    "code": 166
  },
  {
    "name": "Colombia",
    "iso3166Alpha2CountryCode": "CO",
    "iso3166Alpha3CountryCode": "COL",
    "code": 170
  },
  {
    "name": "Comoros (the)",
    "iso3166Alpha2CountryCode": "KM",
    "iso3166Alpha3CountryCode": "COM",
    "code": 174
  },
  {
    "name": "Congo (the Democratic Republic of the)",
    "iso3166Alpha2CountryCode": "CD",
    "iso3166Alpha3CountryCode": "COD",
    "code": 180
  },
  {
    "name": "Congo (the)",
    "iso3166Alpha2CountryCode": "CG",
    "iso3166Alpha3CountryCode": "COG",
    "code": 178
  },
  {
    "name": "Cook Islands (the)",
    "iso3166Alpha2CountryCode": "CK",
    "iso3166Alpha3CountryCode": "COK",
    "code": 184
  },
  {
    "name": "Costa Rica",
    "iso3166Alpha2CountryCode": "CR",
    "iso3166Alpha3CountryCode": "CRI",
    "code": 188
  },
  {
    "name": "Croatia",
    "iso3166Alpha2CountryCode": "HR",
    "iso3166Alpha3CountryCode": "HRV",
    "code": 191
  },
  {
    "name": "Cuba",
    "iso3166Alpha2CountryCode": "CU",
    "iso3166Alpha3CountryCode": "CUB",
    "code": 192
  },
  {
    "name": "Curaçao",
    "iso3166Alpha2CountryCode": "CW",
    "iso3166Alpha3CountryCode": "CUW",
    "code": 531
  },
  {
    "name": "Cyprus",
    "iso3166Alpha2CountryCode": "CY",
    "iso3166Alpha3CountryCode": "CYP",
    "code": 196
  },
  {
    "name": "Czechia",
    "iso3166Alpha2CountryCode": "CZ",
    "iso3166Alpha3CountryCode": "CZE",
    "code": 203
  },
  {
    "name": "Côte d'Ivoire",
    "iso3166Alpha2CountryCode": "CI",
    "iso3166Alpha3CountryCode": "CIV",
    "code": 384
  },
  {
    "name": "Denmark",
    "iso3166Alpha2CountryCode": "DK",
    "iso3166Alpha3CountryCode": "DNK",
    "code": 208
  },
  {
    "name": "Djibouti",
    "iso3166Alpha2CountryCode": "DJ",
    "iso3166Alpha3CountryCode": "DJI",
    "code": 262
  },
  {
    "name": "Dominica",
    "iso3166Alpha2CountryCode": "DM",
    "iso3166Alpha3CountryCode": "DMA",
    "code": 212
  },
  {
    "name": "Dominican Republic (the)",
    "iso3166Alpha2CountryCode": "DO",
    "iso3166Alpha3CountryCode": "DOM",
    "code": 214
  },
  {
    "name": "Ecuador",
    "iso3166Alpha2CountryCode": "EC",
    "iso3166Alpha3CountryCode": "ECU",
    "code": 218
  },
  {
    "name": "Egypt",
    "iso3166Alpha2CountryCode": "EG",
    "iso3166Alpha3CountryCode": "EGY",
    "code": 818
  },
  {
    "name": "El Salvador",
    "iso3166Alpha2CountryCode": "SV",
    "iso3166Alpha3CountryCode": "SLV",
    "code": 222
  },
  {
    "name": "Equatorial Guinea",
    "iso3166Alpha2CountryCode": "GQ",
    "iso3166Alpha3CountryCode": "GNQ",
    "code": 226
  },
  {
    "name": "Eritrea",
    "iso3166Alpha2CountryCode": "ER",
    "iso3166Alpha3CountryCode": "ERI",
    "code": 232
  },
  {
    "name": "Estonia",
    "iso3166Alpha2CountryCode": "EE",
    "iso3166Alpha3CountryCode": "EST",
    "code": 233
  },
  {
    "name": "Eswatini",
    "iso3166Alpha2CountryCode": "SZ",
    "iso3166Alpha3CountryCode": "SWZ",
    "code": 748
  },
  {
    "name": "Ethiopia",
    "iso3166Alpha2CountryCode": "ET",
    "iso3166Alpha3CountryCode": "ETH",
    "code": 231
  },
  {
    "name": "Falkland Islands (the) [Malvinas]",
    "iso3166Alpha2CountryCode": "FK",
    "iso3166Alpha3CountryCode": "FLK",
    "code": 238
  },
  {
    "name": "Faroe Islands (the)",
    "iso3166Alpha2CountryCode": "FO",
    "iso3166Alpha3CountryCode": "FRO",
    "code": 234
  },
  {
    "name": "Fiji",
    "iso3166Alpha2CountryCode": "FJ",
    "iso3166Alpha3CountryCode": "FJI",
    "code": 242
  },
  {
    "name": "Finland",
    "iso3166Alpha2CountryCode": "FI",
    "iso3166Alpha3CountryCode": "FIN",
    "code": 246
  },
  {
    "name": "France",
    "iso3166Alpha2CountryCode": "FR",
    "iso3166Alpha3CountryCode": "FRA",
    "code": 250
  },
  {
    "name": "French Guiana",
    "iso3166Alpha2CountryCode": "GF",
    "iso3166Alpha3CountryCode": "GUF",
    "code": 254
  },
  {
    "name": "French Polynesia",
    "iso3166Alpha2CountryCode": "PF",
    "iso3166Alpha3CountryCode": "PYF",
    "code": 258
  },
  {
    "name": "French Southern Territories (the)",
    "iso3166Alpha2CountryCode": "TF",
    "iso3166Alpha3CountryCode": "ATF",
    "code": 260
  },
  {
    "name": "Gabon",
    "iso3166Alpha2CountryCode": "GA",
    "iso3166Alpha3CountryCode": "GAB",
    "code": 266
  },
  {
    "name": "Gambia (the)",
    "iso3166Alpha2CountryCode": "GM",
    "iso3166Alpha3CountryCode": "GMB",
    "code": 270
  },
  {
    "name": "Georgia",
    "iso3166Alpha2CountryCode": "GE",
    "iso3166Alpha3CountryCode": "GEO",
    "code": 268
  },
  {
    "name": "Germany",
    "iso3166Alpha2CountryCode": "DE",
    "iso3166Alpha3CountryCode": "DEU",
    "code": 276
  },
  {
    "name": "Ghana",
    "iso3166Alpha2CountryCode": "GH",
    "iso3166Alpha3CountryCode": "GHA",
    "code": 288
  },
  {
    "name": "Gibraltar",
    "iso3166Alpha2CountryCode": "GI",
    "iso3166Alpha3CountryCode": "GIB",
    "code": 292
  },
  {
    "name": "Greece",
    "iso3166Alpha2CountryCode": "GR",
    "iso3166Alpha3CountryCode": "GRC",
    "code": 300
  },
  {
    "name": "Greenland",
    "iso3166Alpha2CountryCode": "GL",
    "iso3166Alpha3CountryCode": "GRL",
    "code": 304
  },
  {
    "name": "Grenada",
    "iso3166Alpha2CountryCode": "GD",
    "iso3166Alpha3CountryCode": "GRD",
    "code": 308
  },
  {
    "name": "Guadeloupe",
    "iso3166Alpha2CountryCode": "GP",
    "iso3166Alpha3CountryCode": "GLP",
    "code": 312
  },
  {
    "name": "Guam",
    "iso3166Alpha2CountryCode": "GU",
    "iso3166Alpha3CountryCode": "GUM",
    "code": 316
  },
  {
    "name": "Guatemala",
    "iso3166Alpha2CountryCode": "GT",
    "iso3166Alpha3CountryCode": "GTM",
    "code": 320
  },
  {
    "name": "Guernsey",
    "iso3166Alpha2CountryCode": "GG",
    "iso3166Alpha3CountryCode": "GGY",
    "code": 831
  },
  {
    "name": "Guinea",
    "iso3166Alpha2CountryCode": "GN",
    "iso3166Alpha3CountryCode": "GIN",
    "code": 324
  },
  {
    "name": "Guinea-Bissau",
    "iso3166Alpha2CountryCode": "GW",
    "iso3166Alpha3CountryCode": "GNB",
    "code": 624
  },
  {
    "name": "Guyana",
    "iso3166Alpha2CountryCode": "GY",
    "iso3166Alpha3CountryCode": "GUY",
    "code": 328
  },
  {
    "name": "Haiti",
    "iso3166Alpha2CountryCode": "HT",
    "iso3166Alpha3CountryCode": "HTI",
    "code": 332
  },
  {
    "name": "Heard Island and McDonald Islands",
    "iso3166Alpha2CountryCode": "HM",
    "iso3166Alpha3CountryCode": "HMD",
    "code": 334
  },
  {
    "name": "Holy See (the)",
    "iso3166Alpha2CountryCode": "VA",
    "iso3166Alpha3CountryCode": "VAT",
    "code": 336
  },
  {
    "name": "Honduras",
    "iso3166Alpha2CountryCode": "HN",
    "iso3166Alpha3CountryCode": "HND",
    "code": 340
  },
  {
    "name": "Hong Kong",
    "iso3166Alpha2CountryCode": "HK",
    "iso3166Alpha3CountryCode": "HKG",
    "code": 344
  },
  {
    "name": "Hungary",
    "iso3166Alpha2CountryCode": "HU",
    "iso3166Alpha3CountryCode": "HUN",
    "code": 348
  },
  {
    "name": "Iceland",
    "iso3166Alpha2CountryCode": "IS",
    "iso3166Alpha3CountryCode": "ISL",
    "code": 352
  },
  {
    "name": "India",
    "iso3166Alpha2CountryCode": "IN",
    "iso3166Alpha3CountryCode": "IND",
    "code": 356
  },
  {
    "name": "Indonesia",
    "iso3166Alpha2CountryCode": "ID",
    "iso3166Alpha3CountryCode": "IDN",
    "code": 360
  },
  {
    "name": "Iran (Islamic Republic of)",
    "iso3166Alpha2CountryCode": "IR",
    "iso3166Alpha3CountryCode": "IRN",
    "code": 364
  },
  {
    "name": "Iraq",
    "iso3166Alpha2CountryCode": "IQ",
    "iso3166Alpha3CountryCode": "IRQ",
    "code": 368
  },
  {
    "name": "Ireland",
    "iso3166Alpha2CountryCode": "IE",
    "iso3166Alpha3CountryCode": "IRL",
    "code": 372
  },
  {
    "name": "Isle of Man",
    "iso3166Alpha2CountryCode": "IM",
    "iso3166Alpha3CountryCode": "IMN",
    "code": 833
  },
  {
    "name": "Israel",
    "iso3166Alpha2CountryCode": "IL",
    "iso3166Alpha3CountryCode": "ISR",
    "code": 376
  },
  {
    "name": "Italy",
    "iso3166Alpha2CountryCode": "IT",
    "iso3166Alpha3CountryCode": "ITA",
    "code": 380
  },
  {
    "name": "Jamaica",
    "iso3166Alpha2CountryCode": "JM",
    "iso3166Alpha3CountryCode": "JAM",
    "code": 388
  },
  {
    "name": "Japan",
    "iso3166Alpha2CountryCode": "JP",
    "iso3166Alpha3CountryCode": "JPN",
    "code": 392
  },
  {
    "name": "Jersey",
    "iso3166Alpha2CountryCode": "JE",
    "iso3166Alpha3CountryCode": "JEY",
    "code": 832
  },
  {
    "name": "Jordan",
    "iso3166Alpha2CountryCode": "JO",
    "iso3166Alpha3CountryCode": "JOR",
    "code": 400
  },
  {
    "name": "Kazakhstan",
    "iso3166Alpha2CountryCode": "KZ",
    "iso3166Alpha3CountryCode": "KAZ",
    "code": 398
  },
  {
    "name": "Kenya",
    "iso3166Alpha2CountryCode": "KE",
    "iso3166Alpha3CountryCode": "KEN",
    "code": 404
  },
  {
    "name": "Kiribati",
    "iso3166Alpha2CountryCode": "KI",
    "iso3166Alpha3CountryCode": "KIR",
    "code": 296
  },
  {
    "name": "Korea (the Democratic People's Republic of)",
    "iso3166Alpha2CountryCode": "KP",
    "iso3166Alpha3CountryCode": "PRK",
    "code": 408
  },
  {
    "name": "Korea (the Republic of)",
    "iso3166Alpha2CountryCode": "KR",
    "iso3166Alpha3CountryCode": "KOR",
    "code": 410
  },
  {
    "name": "Kuwait",
    "iso3166Alpha2CountryCode": "KW",
    "iso3166Alpha3CountryCode": "KWT",
    "code": 414
  },
  {
    "name": "Kyrgyzstan",
    "iso3166Alpha2CountryCode": "KG",
    "iso3166Alpha3CountryCode": "KGZ",
    "code": 417
  },
  {
    "name": "Lao People's Democratic Republic (the)",
    "iso3166Alpha2CountryCode": "LA",
    "iso3166Alpha3CountryCode": "LAO",
    "code": 418
  },
  {
    "name": "Latvia",
    "iso3166Alpha2CountryCode": "LV",
    "iso3166Alpha3CountryCode": "LVA",
    "code": 428
  },
  {
    "name": "Lebanon",
    "iso3166Alpha2CountryCode": "LB",
    "iso3166Alpha3CountryCode": "LBN",
    "code": 422
  },
  {
    "name": "Lesotho",
    "iso3166Alpha2CountryCode": "LS",
    "iso3166Alpha3CountryCode": "LSO",
    "code": 426
  },
  {
    "name": "Liberia",
    "iso3166Alpha2CountryCode": "LR",
    "iso3166Alpha3CountryCode": "LBR",
    "code": 430
  },
  {
    "name": "Libya",
    "iso3166Alpha2CountryCode": "LY",
    "iso3166Alpha3CountryCode": "LBY",
    "code": 434
  },
  {
    "name": "Liechtenstein",
    "iso3166Alpha2CountryCode": "LI",
    "iso3166Alpha3CountryCode": "LIE",
    "code": 438
  },
  {
    "name": "Lithuania",
    "iso3166Alpha2CountryCode": "LT",
    "iso3166Alpha3CountryCode": "LTU",
    "code": 440
  },
  {
    "name": "Luxembourg",
    "iso3166Alpha2CountryCode": "LU",
    "iso3166Alpha3CountryCode": "LUX",
    "code": 442
  },
  {
    "name": "Macao",
    "iso3166Alpha2CountryCode": "MO",
    "iso3166Alpha3CountryCode": "MAC",
    "code": 446
  },
  {
    "name": "Madagascar",
    "iso3166Alpha2CountryCode": "MG",
    "iso3166Alpha3CountryCode": "MDG",
    "code": 450
  },
  {
    "name": "Malawi",
    "iso3166Alpha2CountryCode": "MW",
    "iso3166Alpha3CountryCode": "MWI",
    "code": 454
  },
  {
    "name": "Malaysia",
    "iso3166Alpha2CountryCode": "MY",
    "iso3166Alpha3CountryCode": "MYS",
    "code": 458
  },
  {
    "name": "Maldives",
    "iso3166Alpha2CountryCode": "MV",
    "iso3166Alpha3CountryCode": "MDV",
    "code": 462
  },
  {
    "name": "Mali",
    "iso3166Alpha2CountryCode": "ML",
    "iso3166Alpha3CountryCode": "MLI",
    "code": 466
  },
  {
    "name": "Malta",
    "iso3166Alpha2CountryCode": "MT",
    "iso3166Alpha3CountryCode": "MLT",
    "code": 470
  },
  {
    "name": "Marshall Islands (the)",
    "iso3166Alpha2CountryCode": "MH",
    "iso3166Alpha3CountryCode": "MHL",
    "code": 584
  },
  {
    "name": "Martinique",
    "iso3166Alpha2CountryCode": "MQ",
    "iso3166Alpha3CountryCode": "MTQ",
    "code": 474
  },
  {
    "name": "Mauritania",
    "iso3166Alpha2CountryCode": "MR",
    "iso3166Alpha3CountryCode": "MRT",
    "code": 478
  },
  {
    "name": "Mauritius",
    "iso3166Alpha2CountryCode": "MU",
    "iso3166Alpha3CountryCode": "MUS",
    "code": 480
  },
  {
    "name": "Mayotte",
    "iso3166Alpha2CountryCode": "YT",
    "iso3166Alpha3CountryCode": "MYT",
    "code": 175
  },
  {
    "name": "Mexico",
    "iso3166Alpha2CountryCode": "MX",
    "iso3166Alpha3CountryCode": "MEX",
    "code": 484
  },
  {
    "name": "Micronesia (Federated States of)",
    "iso3166Alpha2CountryCode": "FM",
    "iso3166Alpha3CountryCode": "FSM",
    "code": 583
  },
  {
    "name": "Moldova (the Republic of)",
    "iso3166Alpha2CountryCode": "MD",
    "iso3166Alpha3CountryCode": "MDA",
    "code": 498
  },
  {
    "name": "Monaco",
    "iso3166Alpha2CountryCode": "MC",
    "iso3166Alpha3CountryCode": "MCO",
    "code": 492
  },
  {
    "name": "Mongolia",
    "iso3166Alpha2CountryCode": "MN",
    "iso3166Alpha3CountryCode": "MNG",
    "code": 496
  },
  {
    "name": "Montenegro",
    "iso3166Alpha2CountryCode": "ME",
    "iso3166Alpha3CountryCode": "MNE",
    "code": 499
  },
  {
    "name": "Montserrat",
    "iso3166Alpha2CountryCode": "MS",
    "iso3166Alpha3CountryCode": "MSR",
    "code": 500
  },
  {
    "name": "Morocco",
    "iso3166Alpha2CountryCode": "MA",
    "iso3166Alpha3CountryCode": "MAR",
    "code": 504
  },
  {
    "name": "Mozambique",
    "iso3166Alpha2CountryCode": "MZ",
    "iso3166Alpha3CountryCode": "MOZ",
    "code": 508
  },
  {
    "name": "Myanmar",
    "iso3166Alpha2CountryCode": "MM",
    "iso3166Alpha3CountryCode": "MMR",
    "code": 104
  },
  {
    "name": "Namibia",
    "iso3166Alpha2CountryCode": "NA",
    "iso3166Alpha3CountryCode": "NAM",
    "code": 516
  },
  {
    "name": "Nauru",
    "iso3166Alpha2CountryCode": "NR",
    "iso3166Alpha3CountryCode": "NRU",
    "code": 520
  },
  {
    "name": "Nepal",
    "iso3166Alpha2CountryCode": "NP",
    "iso3166Alpha3CountryCode": "NPL",
    "code": 524
  },
  {
    "name": "Netherlands (the)",
    "iso3166Alpha2CountryCode": "NL",
    "iso3166Alpha3CountryCode": "NLD",
    "code": 528
  },
  {
    "name": "New Caledonia",
    "iso3166Alpha2CountryCode": "NC",
    "iso3166Alpha3CountryCode": "NCL",
    "code": 540
  },
  {
    "name": "New Zealand",
    "iso3166Alpha2CountryCode": "NZ",
    "iso3166Alpha3CountryCode": "NZL",
    "code": 554
  },
  {
    "name": "Nicaragua",
    "iso3166Alpha2CountryCode": "NI",
    "iso3166Alpha3CountryCode": "NIC",
    "code": 558
  },
  {
    "name": "Niger (the)",
    "iso3166Alpha2CountryCode": "NE",
    "iso3166Alpha3CountryCode": "NER",
    "code": 562
  },
  {
    "name": "Nigeria",
    "iso3166Alpha2CountryCode": "NG",
    "iso3166Alpha3CountryCode": "NGA",
    "code": 566
  },
  {
    "name": "Niue",
    "iso3166Alpha2CountryCode": "NU",
    "iso3166Alpha3CountryCode": "NIU",
    "code": 570
  },
  {
    "name": "Norfolk Island",
    "iso3166Alpha2CountryCode": "NF",
    "iso3166Alpha3CountryCode": "NFK",
    "code": 574
  },
  {
    "name": "North Macedonia",
    "iso3166Alpha2CountryCode": "MK",
    "iso3166Alpha3CountryCode": "MKD",
    "code": 807
  },
  {
    "name": "Northern Mariana Islands (the)",
    "iso3166Alpha2CountryCode": "MP",
    "iso3166Alpha3CountryCode": "MNP",
    "code": 580
  },
  {
    "name": "Norway",
    "iso3166Alpha2CountryCode": "NO",
    "iso3166Alpha3CountryCode": "NOR",
    "code": 578
  },
  {
    "name": "Oman",
    "iso3166Alpha2CountryCode": "OM",
    "iso3166Alpha3CountryCode": "OMN",
    "code": 512
  },
  {
    "name": "Pakistan",
    "iso3166Alpha2CountryCode": "PK",
    "iso3166Alpha3CountryCode": "PAK",
    "code": 586
  },
  {
    "name": "Palau",
    "iso3166Alpha2CountryCode": "PW",
    "iso3166Alpha3CountryCode": "PLW",
    "code": 585
  },
  {
    "name": "Palestine, State of",
    "iso3166Alpha2CountryCode": "PS",
    "iso3166Alpha3CountryCode": "PSE",
    "code": 275
  },
  {
    "name": "Panama",
    "iso3166Alpha2CountryCode": "PA",
    "iso3166Alpha3CountryCode": "PAN",
    "code": 591
  },
  {
    "name": "Papua New Guinea",
    "iso3166Alpha2CountryCode": "PG",
    "iso3166Alpha3CountryCode": "PNG",
    "code": 598
  },
  {
    "name": "Paraguay",
    "iso3166Alpha2CountryCode": "PY",
    "iso3166Alpha3CountryCode": "PRY",
    "code": 600
  },
  {
    "name": "Peru",
    "iso3166Alpha2CountryCode": "PE",
    "iso3166Alpha3CountryCode": "PER",
    "code": 604
  },
  {
    "name": "Philippines (the)",
    "iso3166Alpha2CountryCode": "PH",
    "iso3166Alpha3CountryCode": "PHL",
    "code": 608
  },
  {
    "name": "Pitcairn",
    "iso3166Alpha2CountryCode": "PN",
    "iso3166Alpha3CountryCode": "PCN",
    "code": 612
  },
  {
    "name": "Poland",
    "iso3166Alpha2CountryCode": "PL",
    "iso3166Alpha3CountryCode": "POL",
    "code": 616
  },
  {
    "name": "Portugal",
    "iso3166Alpha2CountryCode": "PT",
    "iso3166Alpha3CountryCode": "PRT",
    "code": 620
  },
  {
    "name": "Puerto Rico",
    "iso3166Alpha2CountryCode": "PR",
    "iso3166Alpha3CountryCode": "PRI",
    "code": 630
  },
  {
    "name": "Qatar",
    "iso3166Alpha2CountryCode": "QA",
    "iso3166Alpha3CountryCode": "QAT",
    "code": 634
  },
  {
    "name": "Romania",
    "iso3166Alpha2CountryCode": "RO",
    "iso3166Alpha3CountryCode": "ROU",
    "code": 642
  },
  {
    "name": "Russian Federation (the)",
    "iso3166Alpha2CountryCode": "RU",
    "iso3166Alpha3CountryCode": "RUS",
    "code": 643
  },
  {
    "name": "Rwanda",
    "iso3166Alpha2CountryCode": "RW",
    "iso3166Alpha3CountryCode": "RWA",
    "code": 646
  },
  {
    "name": "Réunion",
    "iso3166Alpha2CountryCode": "RE",
    "iso3166Alpha3CountryCode": "REU",
    "code": 638
  },
  {
    "name": "Saint Barthélemy",
    "iso3166Alpha2CountryCode": "BL",
    "iso3166Alpha3CountryCode": "BLM",
    "code": 652
  },
  {
    "name": "Saint Helena, Ascension and Tristan da Cunha",
    "iso3166Alpha2CountryCode": "SH",
    "iso3166Alpha3CountryCode": "SHN",
    "code": 654
  },
  {
    "name": "Saint Kitts and Nevis",
    "iso3166Alpha2CountryCode": "KN",
    "iso3166Alpha3CountryCode": "KNA",
    "code": 659
  },
  {
    "name": "Saint Lucia",
    "iso3166Alpha2CountryCode": "LC",
    "iso3166Alpha3CountryCode": "LCA",
    "code": 662
  },
  {
    "name": "Saint Martin (French part)",
    "iso3166Alpha2CountryCode": "MF",
    "iso3166Alpha3CountryCode": "MAF",
    "code": 663
  },
  {
    "name": "Saint Pierre and Miquelon",
    "iso3166Alpha2CountryCode": "PM",
    "iso3166Alpha3CountryCode": "SPM",
    "code": 666
  },
  {
    "name": "Saint Vincent and the Grenadines",
    "iso3166Alpha2CountryCode": "VC",
    "iso3166Alpha3CountryCode": "VCT",
    "code": 670
  },
  {
    "name": "Samoa",
    "iso3166Alpha2CountryCode": "WS",
    "iso3166Alpha3CountryCode": "WSM",
    "code": 882
  },
  {
    "name": "San Marino",
    "iso3166Alpha2CountryCode": "SM",
    "iso3166Alpha3CountryCode": "SMR",
    "code": 674
  },
  {
    "name": "Sao Tome and Principe",
    "iso3166Alpha2CountryCode": "ST",
    "iso3166Alpha3CountryCode": "STP",
    "code": 678
  },
  {
    "name": "Saudi Arabia",
    "iso3166Alpha2CountryCode": "SA",
    "iso3166Alpha3CountryCode": "SAU",
    "code": 682
  },
  {
    "name": "Senegal",
    "iso3166Alpha2CountryCode": "SN",
    "iso3166Alpha3CountryCode": "SEN",
    "code": 686
  },
  {
    "name": "Serbia",
    "iso3166Alpha2CountryCode": "RS",
    "iso3166Alpha3CountryCode": "SRB",
    "code": 688
  },
  {
    "name": "Seychelles",
    "iso3166Alpha2CountryCode": "SC",
    "iso3166Alpha3CountryCode": "SYC",
    "code": 690
  },
  {
    "name": "Sierra Leone",
    "iso3166Alpha2CountryCode": "SL",
    "iso3166Alpha3CountryCode": "SLE",
    "code": 694
  },
  {
    "name": "Singapore",
    "iso3166Alpha2CountryCode": "SG",
    "iso3166Alpha3CountryCode": "SGP",
    "code": 702
  },
  {
    "name": "Sint Maarten (Dutch part)",
    "iso3166Alpha2CountryCode": "SX",
    "iso3166Alpha3CountryCode": "SXM",
    "code": 534
  },
  {
    "name": "Slovakia",
    "iso3166Alpha2CountryCode": "SK",
    "iso3166Alpha3CountryCode": "SVK",
    "code": 703
  },
  {
    "name": "Slovenia",
    "iso3166Alpha2CountryCode": "SI",
    "iso3166Alpha3CountryCode": "SVN",
    "code": 705
  },
  {
    "name": "Solomon Islands",
    "iso3166Alpha2CountryCode": "SB",
    "iso3166Alpha3CountryCode": "SLB",
    "code": 90
  },
  {
    "name": "Somalia",
    "iso3166Alpha2CountryCode": "SO",
    "iso3166Alpha3CountryCode": "SOM",
    "code": 706
  },
  {
    "name": "South Africa",
    "iso3166Alpha2CountryCode": "ZA",
    "iso3166Alpha3CountryCode": "ZAF",
    "code": 710
  },
  {
    "name": "South Georgia and the South Sandwich Islands",
    "iso3166Alpha2CountryCode": "GS",
    "iso3166Alpha3CountryCode": "SGS",
    "code": 239
  },
  {
    "name": "South Sudan",
    "iso3166Alpha2CountryCode": "SS",
    "iso3166Alpha3CountryCode": "SSD",
    "code": 728
  },
  {
    "name": "Spain",
    "iso3166Alpha2CountryCode": "ES",
    "iso3166Alpha3CountryCode": "ESP",
    "code": 724
  },
  {
    "name": "Sri Lanka",
    "iso3166Alpha2CountryCode": "LK",
    "iso3166Alpha3CountryCode": "LKA",
    "code": 144
  },
  {
    "name": "Sudan (the)",
    "iso3166Alpha2CountryCode": "SD",
    "iso3166Alpha3CountryCode": "SDN",
    "code": 729
  },
  {
    "name": "Suriname",
    "iso3166Alpha2CountryCode": "SR",
    "iso3166Alpha3CountryCode": "SUR",
    "code": 740
  },
  {
    "name": "Svalbard and Jan Mayen",
    "iso3166Alpha2CountryCode": "SJ",
    "iso3166Alpha3CountryCode": "SJM",
    "code": 744
  },
  {
    "name": "Sweden",
    "iso3166Alpha2CountryCode": "SE",
    "iso3166Alpha3CountryCode": "SWE",
    "code": 752
  },
  {
    "name": "Switzerland",
    "iso3166Alpha2CountryCode": "CH",
    "iso3166Alpha3CountryCode": "CHE",
    "code": 756
  },
  {
    "name": "Syrian Arab Republic (the)",
    "iso3166Alpha2CountryCode": "SY",
    "iso3166Alpha3CountryCode": "SYR",
    "code": 760
  },
  {
    "name": "Taiwan (Province of China)",
    "iso3166Alpha2CountryCode": "TW",
    "iso3166Alpha3CountryCode": "TWN",
    "code": 158
  },
  {
    "name": "Tajikistan",
    "iso3166Alpha2CountryCode": "TJ",
    "iso3166Alpha3CountryCode": "TJK",
    "code": 762
  },
  {
    "name": "Tanzania, the United Republic of",
    "iso3166Alpha2CountryCode": "TZ",
    "iso3166Alpha3CountryCode": "TZA",
    "code": 834
  },
  {
    "name": "Thailand",
    "iso3166Alpha2CountryCode": "TH",
    "iso3166Alpha3CountryCode": "THA",
    "code": 764
  },
  {
    "name": "Timor-Leste",
    "iso3166Alpha2CountryCode": "TL",
    "iso3166Alpha3CountryCode": "TLS",
    "code": 626
  },
  {
    "name": "Togo",
    "iso3166Alpha2CountryCode": "TG",
    "iso3166Alpha3CountryCode": "TGO",
    "code": 768
  },
  {
    "name": "Tokelau",
    "iso3166Alpha2CountryCode": "TK",
    "iso3166Alpha3CountryCode": "TKL",
    "code": 772
  },
  {
    "name": "Tonga",
    "iso3166Alpha2CountryCode": "TO",
    "iso3166Alpha3CountryCode": "TON",
    "code": 776
  },
  {
    "name": "Trinidad and Tobago",
    "iso3166Alpha2CountryCode": "TT",
    "iso3166Alpha3CountryCode": "TTO",
    "code": 780
  },
  {
    "name": "Tunisia",
    "iso3166Alpha2CountryCode": "TN",
    "iso3166Alpha3CountryCode": "TUN",
    "code": 788
  },
  {
    "name": "Turkey",
    "iso3166Alpha2CountryCode": "TR",
    "iso3166Alpha3CountryCode": "TUR",
    "code": 792
  },
  {
    "name": "Turkmenistan",
    "iso3166Alpha2CountryCode": "TM",
    "iso3166Alpha3CountryCode": "TKM",
    "code": 795
  },
  {
    "name": "Turks and Caicos Islands (the)",
    "iso3166Alpha2CountryCode": "TC",
    "iso3166Alpha3CountryCode": "TCA",
    "code": 796
  },
  {
    "name": "Tuvalu",
    "iso3166Alpha2CountryCode": "TV",
    "iso3166Alpha3CountryCode": "TUV",
    "code": 798
  },
  {
    "name": "Uganda",
    "iso3166Alpha2CountryCode": "UG",
    "iso3166Alpha3CountryCode": "UGA",
    "code": 800
  },
  {
    "name": "Ukraine",
    "iso3166Alpha2CountryCode": "UA",
    "iso3166Alpha3CountryCode": "UKR",
    "code": 804
  },
  {
    "name": "United Arab Emirates (the)",
    "iso3166Alpha2CountryCode": "AE",
    "iso3166Alpha3CountryCode": "ARE",
    "code": 784
  },
  {
    "name": "United Kingdom of Great Britain and Northern Ireland (the)",
    "iso3166Alpha2CountryCode": "GB",
    "iso3166Alpha3CountryCode": "GBR",
    "code": 826
  },
  {
    "name": "United States Minor Outlying Islands (the)",
    "iso3166Alpha2CountryCode": "UM",
    "iso3166Alpha3CountryCode": "UMI",
    "code": 581
  },
  {
    "name": "United States of America (the)",
    "iso3166Alpha2CountryCode": "US",
    "iso3166Alpha3CountryCode": "USA",
    "code": 840
  },
  {
    "name": "Uruguay",
    "iso3166Alpha2CountryCode": "UY",
    "iso3166Alpha3CountryCode": "URY",
    "code": 858
  },
  {
    "name": "Uzbekistan",
    "iso3166Alpha2CountryCode": "UZ",
    "iso3166Alpha3CountryCode": "UZB",
    "code": 860
  },
  {
    "name": "Vanuatu",
    "iso3166Alpha2CountryCode": "VU",
    "iso3166Alpha3CountryCode": "VUT",
    "code": 548
  },
  {
    "name": "Venezuela (Bolivarian Republic of)",
    "iso3166Alpha2CountryCode": "VE",
    "iso3166Alpha3CountryCode": "VEN",
    "code": 862
  },
  {
    "name": "Viet Nam",
    "iso3166Alpha2CountryCode": "VN",
    "iso3166Alpha3CountryCode": "VNM",
    "code": 704
  },
  {
    "name": "Virgin Islands (British)",
    "iso3166Alpha2CountryCode": "VG",
    "iso3166Alpha3CountryCode": "VGB",
    "code": 92
  },
  {
    "name": "Virgin Islands (U.S.)",
    "iso3166Alpha2CountryCode": "VI",
    "iso3166Alpha3CountryCode": "VIR",
    "code": 850
  },
  {
    "name": "Wallis and Futuna",
    "iso3166Alpha2CountryCode": "WF",
    "iso3166Alpha3CountryCode": "WLF",
    "code": 876
  },
  {
    "name": "Western Sahara*",
    "iso3166Alpha2CountryCode": "EH",
    "iso3166Alpha3CountryCode": "ESH",
    "code": 732
  },
  {
    "name": "Yemen",
    "iso3166Alpha2CountryCode": "YE",
    "iso3166Alpha3CountryCode": "YEM",
    "code": 887
  },
  {
    "name": "Zambia",
    "iso3166Alpha2CountryCode": "ZM",
    "iso3166Alpha3CountryCode": "ZMB",
    "code": 894
  },
  {
    "name": "Zimbabwe",
    "iso3166Alpha2CountryCode": "ZW",
    "iso3166Alpha3CountryCode": "ZWE",
    "code": 716
  },
  {
    "name": "Åland Islands",
    "iso3166Alpha2CountryCode": "AX",
    "iso3166Alpha3CountryCode": "ALA",
    "code": 248
  }
]
